TruthDarePy/__init__.py
TruthDarePy-2.0.6.dist-info/LICENSE
TruthDarePy-2.0.6.dist-info/METADATA
TruthDarePy-2.0.6.dist-info/WHEEL
TruthDarePy-2.0.6.dist-info/top_level.txt
TruthDarePy-2.0.6.dist-info/RECORD
