Metadata-Version: 2.1
Name: TruthDarePy
Version: 2.0.6
Summary: Truth Dare Fun Api
Home-page: https://github.com/Awesome-Prince/Tg-Truth-Dare.git
Author: Awesome-Prince
Author-email: DarlingPrince@protonmail.com
License: License :: OSI Approved :: GNU Lesser General Public License v3 (LGPLv3)
Requires-Python: >=3.6
License-File: LICENSE
Requires-Dist: requests
